TORCphysics/Examples/Example_1.ipynb
TORCphysics/Examples/Example_2.ipynb
TORCphysics/Examples/Example_3.ipynb
TORCphysics/Examples/Example_4.ipynb
TORCphysics/Examples/README.md
TORCphysics/Examples/__init__.py
TORCphysics/Examples/circuit.csv
TORCphysics/Examples/environment_1.csv
TORCphysics/Examples/environment_2.csv
TORCphysics/Examples/environment_3.csv
TORCphysics/Examples/environment_4.csv
TORCphysics/Examples/sites_1.csv
TORCphysics/Examples/sites_2.csv
TORCphysics/Examples/sites_3.csv
TORCphysics/__init__.py
TORCphysics/logo.svg
TORCphysics/src/Analysis/__init__.py
TORCphysics/src/Analysis/mechanical_model.py
TORCphysics/src/Analysis/output.npy
TORCphysics/src/Analysis/params.py
TORCphysics/src/Analysis/plot_avg-cross-correlation.py
TORCphysics/src/Analysis/plot_c_animation_v3.py
TORCphysics/src/Analysis/plot_cross-correlation_v4.py
TORCphysics/src/Analysis/plot_gsigma.py
TORCphysics/src/Analysis/plot_outputs.py
TORCphysics/src/Analysis/plot_promoter_curves.py
TORCphysics/src/Analysis/plot_signals.py
TORCphysics/src/Analysis/plot_topo_curves.py
TORCphysics/src/Analysis/promoter_curves.pdf
TORCphysics/src/Analysis/promoter_curves.png
TORCphysics/src/Analysis/sigma_curve.pdf
TORCphysics/src/Analysis/statistical_model.py
TORCphysics/src/Analysis/topo_curves.pdf
TORCphysics/src/Analysis/topo_curves.png
TORCphysics/src/__init__.py
TORCphysics/src/analysis.py
TORCphysics/src/binding_model.py
TORCphysics/src/circuit.py
TORCphysics/src/cli.py
TORCphysics/src/effect_model.py
TORCphysics/src/environment.py
TORCphysics/src/enzyme.py
TORCphysics/src/enzyme_shapes/RNAP.png
TORCphysics/src/enzyme_shapes/gyrase.png
TORCphysics/src/enzyme_shapes/lacI.png
TORCphysics/src/enzyme_shapes/ori.png
TORCphysics/src/enzyme_shapes/topoI.png
TORCphysics/src/extra_tools/__init__.py
TORCphysics/src/extra_tools/add_enzyme.py
TORCphysics/src/extra_tools/parallelization_tools.py
TORCphysics/src/extra_tools/parameter_search.py
TORCphysics/src/extra_tools/topo_calibration_tools.py
torcphysics-0.0.2.dist-info/LICENSE
torcphysics-0.0.2.dist-info/METADATA
torcphysics-0.0.2.dist-info/WHEEL
torcphysics-0.0.2.dist-info/entry_points.txt
torcphysics-0.0.2.dist-info/RECORD
