Metadata-Version: 2.3
Name: TORCphysics
Version: 0.0.2
Summary: A physics-based simulation platform of supercoiling-mediated regulation of gene expression.
License: GPL-3.0-or-later
Author: Victor Manuel Velasco Berrelleza
Requires-Python: >=3.10,<4.0
Classifier: License :: OSI Approved :: GNU General Public License v3 or later (GPLv3+)
Classifier: Programming Language :: Python :: 3
Classifier: Programming Language :: Python :: 3.10
Classifier: Programming Language :: Python :: 3.11
Classifier: Programming Language :: Python :: 3.12
Classifier: Programming Language :: Python :: 3.13
Requires-Dist: matplotlib (>=3.7.0,<4.0.0)
Requires-Dist: numpy (>=1.24.2,<2.0.0)
Requires-Dist: pandas (>=1.5.3,<2.0.0)
Requires-Dist: scipy (>=1.13.0,<2.0.0)
